edapp_python_sdk/__init__.py
edapp_python_sdk/edapppy.py
edapp_python_sdk/main.py
edapp_python_sdk/sql_models.py
edapp_python_sdk-0.1.12.dist-info/entry_points.txt
edapp_python_sdk-0.1.12.dist-info/LICENSE
edapp_python_sdk-0.1.12.dist-info/WHEEL
edapp_python_sdk-0.1.12.dist-info/METADATA
edapp_python_sdk-0.1.12.dist-info/RECORD
